pltpublish/__init__.py
pltpublish/pltpublish.py
pltpublish/py.typed
pltpublish-1.0.3.dist-info/LICENSE
pltpublish-1.0.3.dist-info/METADATA
pltpublish-1.0.3.dist-info/WHEEL
pltpublish-1.0.3.dist-info/RECORD
