Metadata-Version: 2.1
Name: pltpublish
Version: 1.0.3
Summary: Utility package that takes care of configuring Matplotlib for publication-ready figures!
Home-page: https://github.com/Theomat/pltpublish
License: MIT
Author: Théo Matricon
Author-email: theomatricon@gmail.com
Requires-Python: >=3.7.1
Classifier: License :: OSI Approved :: MIT License
Classifier: Programming Language :: Python :: 3
Classifier: Programming Language :: Python :: 3.8
Classifier: Programming Language :: Python :: 3.9
Classifier: Programming Language :: Python :: 3.10
Classifier: Programming Language :: Python :: 3.11
Classifier: Programming Language :: Python :: 3.12
Requires-Dist: matplotlib (>=3.0)
Project-URL: Repository, https://github.com/Theomat/pltpublish
